auto_reflection/__init__.py
auto_reflection/section.py
auto_reflection/titles.py
auto_reflection/topics.py
auto_reflection/include/__init__.py
auto_reflection/include/claude_AssistantAgent.py
auto_reflection/include/common.py
auto_reflection/include/openai_AssistantAgent.py
auto_reflection/include/utils.py
auto_reflection/include/agents/__init__.py
auto_reflection/include/agents/reflection_bloggers.py
auto_reflection/include/config/AppConfig.py
auto_reflection/include/config/Config.py
auto_reflection/include/config/__init__.py
auto_reflection/include/config/init_config.py
auto_reflection-1.0.3.dist-info/LICENSE
auto_reflection-1.0.3.dist-info/METADATA
auto_reflection-1.0.3.dist-info/WHEEL
auto_reflection-1.0.3.dist-info/entry_points.txt
auto_reflection-1.0.3.dist-info/top_level.txt
auto_reflection-1.0.3.dist-info/RECORD
