Metadata-Version: 2.1
Name: auto_reflection
Version: 1.0.3
Summary: An AI-powered blog-writing pipeline with reflection-based agents using YAML configuration and mock data handling
Home-page: https://github.com/myaichat/auto_reflection
Author: Alex Buzunov
Author-email: alex_buz@yahoo.com
Project-URL: Source, https://github.com/myaichat/auto_reflection
Project-URL: Tracker, https://github.com/myaichat/auto_reflection/issues
Classifier: Development Status :: 5 - Production/Stable
Classifier: Intended Audience :: Developers
Classifier: License :: OSI Approved :: MIT License
Classifier: Programming Language :: Python :: 3
Classifier: Programming Language :: Python :: 3.8
Classifier: Programming Language :: Python :: 3.9
Classifier: Programming Language :: Python :: 3.10
Classifier: Topic :: Software Development :: Libraries
Classifier: Operating System :: OS Independent
Requires-Python: >=3.8
License-File: LICENSE
Requires-Dist: PyYAML
Requires-Dist: pypubsub
Requires-Dist: openai
